[
    {
        "id": 1,
        "logo": "spec.png",
        "name": "Specsavers Denmark",
        "com_id": 13950,
        "lae_id": 4567,
        "size": 57,
        "status": "active"
    },
    {
        "id": 2,
        "logo": "yunar.png",
        "name": "Yunar",
        "com_id": 13955,
        "lae_id": 3254,
        "size": 43,
        "status": "active"
    },
    {
        "id": 3,
        "logo": "coca.png",
        "name": "Coca-Cola",
        "com_id": 13987,
        "lae_id": 5487,
        "size": 27,
        "status": "active"
    },
    {
        "id": 4,
        "logo": "helly.png",
        "name": "Helly Hansen",
        "com_id": 13654,
        "lae_id": 1236,
        "size": 80,
        "status": "active"
    },
    {
        "id": 5,
        "logo": "brand.png",
        "name": "Brand Enterprise",
        "com_id": 13250,
        "lae_id": 3154,
        "size": 410,
        "status": "active"
    },
    {
        "id": 6,
        "logo": "mb.png",
        "name": "Mercedes-Benz Europe",
        "com_id": 12987,
        "lae_id": 3187,
        "size": 128,
        "status": "active"
    },
    {
        "id": 7,
        "logo": "bmw.png",
        "name": "BMW Nordic",
        "com_id": 12282,
        "lae_id": 3648,
        "size": 75,
        "status": "active"
    }
]